pngbin/ChainReader.py
pngbin/ChainWriter.py
pngbin/DecryptReader.py
pngbin/EncryptWriter.py
pngbin/Reader.py
pngbin/Writer.py
pngbin/__init__.py
PngBin-0.1.0.dist-info/LICENSE
PngBin-0.1.0.dist-info/METADATA
PngBin-0.1.0.dist-info/WHEEL
PngBin-0.1.0.dist-info/top_level.txt
PngBin-0.1.0.dist-info/RECORD
