Metadata-Version: 2.1
Name: PngBin
Version: 0.1.0
Summary: Convert any binary data to a PNG image file and vice versa.
Home-page: https://github.com/TheYoke/PngBin
Author: Nathan Young
Author-email: theyoke3@gmail.com
License: MIT
Platform: UNKNOWN
Classifier: Programming Language :: Python :: 3
Classifier: License :: OSI Approved :: MIT License
Classifier: Operating System :: OS Independent
Requires-Python: >=3.6
Requires-Dist: cryptography
